{
  "date": "2025-11-03",
  "total_events": 7,
  "new_events": 7,
  "platforms": {
    "eastmoney": 7
  },
  "events": [
    {
      "platform": "eastmoney",
      "event_id": "em_jjsj_20251103230000_2368649572036177283",
      "original_id": "2025-11-03 23:00:00_美国：ISM：制造业PMI：供应商交付(报告期:2025年10月)",
      "event_date": "2025-11-03",
      "event_time": "23:00:00",
      "event_datetime": "2025-11-03 23:00:00",
      "title": "美国：ISM：制造业PMI：供应商交付(报告期:2025年10月)",
      "content": null,
      "category": "经济数据",
      "importance": 4,
      "country": "美国",
      "city": null,
      "stocks": [],
      "concepts": [],
      "themes": [],
      "data_status": "ACTIVE",
      "is_new": true,
      "discovery_date": "2025-09-19",
      "raw_data": {
        "Name": "美国：ISM：制造业PMI：供应商交付(报告期:2025年10月)",
        "City": "美国"
      },
      "created_at": "2025-09-19T14:15:16.919494"
    },
    {
      "platform": "eastmoney",
      "event_id": "em_jjsj_20251103230000_7020043944904158442",
      "original_id": "2025-11-03 23:00:00_美国：ISM：制造业PMI：自有库存(报告期:2025年10月)",
      "event_date": "2025-11-03",
      "event_time": "23:00:00",
      "event_datetime": "2025-11-03 23:00:00",
      "title": "美国：ISM：制造业PMI：自有库存(报告期:2025年10月)",
      "content": null,
      "category": "经济数据",
      "importance": 4,
      "country": "美国",
      "city": null,
      "stocks": [],
      "concepts": [],
      "themes": [],
      "data_status": "ACTIVE",
      "is_new": true,
      "discovery_date": "2025-09-19",
      "raw_data": {
        "Name": "美国：ISM：制造业PMI：自有库存(报告期:2025年10月)",
        "City": "美国"
      },
      "created_at": "2025-09-19T14:15:16.919501"
    },
    {
      "platform": "eastmoney",
      "event_id": "em_jjsj_20251103230000_-4313134247702416727",
      "original_id": "2025-11-03 23:00:00_美国：ISM:制造业PMI(报告期:2025年10月)",
      "event_date": "2025-11-03",
      "event_time": "23:00:00",
      "event_datetime": "2025-11-03 23:00:00",
      "title": "美国：ISM:制造业PMI(报告期:2025年10月)",
      "content": null,
      "category": "经济数据",
      "importance": 4,
      "country": "美国",
      "city": null,
      "stocks": [],
      "concepts": [],
      "themes": [],
      "data_status": "ACTIVE",
      "is_new": true,
      "discovery_date": "2025-09-19",
      "raw_data": {
        "Name": "美国：ISM:制造业PMI(报告期:2025年10月)",
        "City": "美国"
      },
      "created_at": "2025-09-19T14:15:16.919508"
    },
    {
      "platform": "eastmoney",
      "event_id": "em_jjsj_20251103230000_3582848688835548626",
      "original_id": "2025-11-03 23:00:00_美国：ISM：制造业PMI：物价(报告期:2025年10月)",
      "event_date": "2025-11-03",
      "event_time": "23:00:00",
      "event_datetime": "2025-11-03 23:00:00",
      "title": "美国：ISM：制造业PMI：物价(报告期:2025年10月)",
      "content": null,
      "category": "经济数据",
      "importance": 4,
      "country": "美国",
      "city": null,
      "stocks": [],
      "concepts": [],
      "themes": [],
      "data_status": "ACTIVE",
      "is_new": true,
      "discovery_date": "2025-09-19",
      "raw_data": {
        "Name": "美国：ISM：制造业PMI：物价(报告期:2025年10月)",
        "City": "美国"
      },
      "created_at": "2025-09-19T14:15:16.919515"
    },
    {
      "platform": "eastmoney",
      "event_id": "em_jjsj_20251103230000_-4262124645623920741",
      "original_id": "2025-11-03 23:00:00_美国：ISM：制造业PMI：新订单(报告期:2025年10月)",
      "event_date": "2025-11-03",
      "event_time": "23:00:00",
      "event_datetime": "2025-11-03 23:00:00",
      "title": "美国：ISM：制造业PMI：新订单(报告期:2025年10月)",
      "content": null,
      "category": "经济数据",
      "importance": 4,
      "country": "美国",
      "city": null,
      "stocks": [],
      "concepts": [],
      "themes": [],
      "data_status": "ACTIVE",
      "is_new": true,
      "discovery_date": "2025-09-19",
      "raw_data": {
        "Name": "美国：ISM：制造业PMI：新订单(报告期:2025年10月)",
        "City": "美国"
      },
      "created_at": "2025-09-19T14:15:16.919549"
    },
    {
      "platform": "eastmoney",
      "event_id": "em_jjsj_20251103230000_-4242945427192717020",
      "original_id": "2025-11-03 23:00:00_美国：ISM：制造业PMI：产出(报告期:2025年10月)",
      "event_date": "2025-11-03",
      "event_time": "23:00:00",
      "event_datetime": "2025-11-03 23:00:00",
      "title": "美国：ISM：制造业PMI：产出(报告期:2025年10月)",
      "content": null,
      "category": "经济数据",
      "importance": 4,
      "country": "美国",
      "city": null,
      "stocks": [],
      "concepts": [],
      "themes": [],
      "data_status": "ACTIVE",
      "is_new": true,
      "discovery_date": "2025-09-19",
      "raw_data": {
        "Name": "美国：ISM：制造业PMI：产出(报告期:2025年10月)",
        "City": "美国"
      },
      "created_at": "2025-09-19T14:15:16.919557"
    },
    {
      "platform": "eastmoney",
      "event_id": "em_jjsj_20251103230000_-7629237244430317728",
      "original_id": "2025-11-03 23:00:00_美国：ISM：制造业PMI：就业(报告期:2025年10月)",
      "event_date": "2025-11-03",
      "event_time": "23:00:00",
      "event_datetime": "2025-11-03 23:00:00",
      "title": "美国：ISM：制造业PMI：就业(报告期:2025年10月)",
      "content": null,
      "category": "经济数据",
      "importance": 4,
      "country": "美国",
      "city": null,
      "stocks": [],
      "concepts": [],
      "themes": [],
      "data_status": "ACTIVE",
      "is_new": true,
      "discovery_date": "2025-09-19",
      "raw_data": {
        "Name": "美国：ISM：制造业PMI：就业(报告期:2025年10月)",
        "City": "美国"
      },
      "created_at": "2025-09-19T14:15:16.919565"
    }
  ]
}