{
  "date": "2025-11-03",
  "total_events": 7,
  "new_events": 7,
  "platforms": {
    "eastmoney": 7
  },
  "events": [
    {
      "platform": "eastmoney",
      "event_id": "em_jjsj_20251103230000_8403303458949518993",
      "original_id": "2025-11-03 23:00:00_美国：ISM：制造业PMI：供应商交付(报告期:2025年10月)",
      "event_date": "2025-11-03",
      "event_time": "23:00:00",
      "event_datetime": "2025-11-03 23:00:00",
      "title": "美国：ISM：制造业PMI：供应商交付(报告期:2025年10月)",
      "content": null,
      "category": "经济数据",
      "importance": 4,
      "country": "美国",
      "city": null,
      "stocks": [],
      "concepts": [],
      "themes": [],
      "data_status": "ACTIVE",
      "is_new": true,
      "discovery_date": "2025-10-11",
      "raw_data": {
        "Name": "美国：ISM：制造业PMI：供应商交付(报告期:2025年10月)",
        "City": "美国"
      },
      "created_at": "2025-10-11T14:11:59.732616"
    },
    {
      "platform": "eastmoney",
      "event_id": "em_jjsj_20251103230000_-8852543322773101464",
      "original_id": "2025-11-03 23:00:00_美国：ISM：制造业PMI：自有库存(报告期:2025年10月)",
      "event_date": "2025-11-03",
      "event_time": "23:00:00",
      "event_datetime": "2025-11-03 23:00:00",
      "title": "美国：ISM：制造业PMI：自有库存(报告期:2025年10月)",
      "content": null,
      "category": "经济数据",
      "importance": 4,
      "country": "美国",
      "city": null,
      "stocks": [],
      "concepts": [],
      "themes": [],
      "data_status": "ACTIVE",
      "is_new": true,
      "discovery_date": "2025-10-11",
      "raw_data": {
        "Name": "美国：ISM：制造业PMI：自有库存(报告期:2025年10月)",
        "City": "美国"
      },
      "created_at": "2025-10-11T14:11:59.732623"
    },
    {
      "platform": "eastmoney",
      "event_id": "em_jjsj_20251103230000_4599237860377632727",
      "original_id": "2025-11-03 23:00:00_美国：ISM:制造业PMI(报告期:2025年10月)",
      "event_date": "2025-11-03",
      "event_time": "23:00:00",
      "event_datetime": "2025-11-03 23:00:00",
      "title": "美国：ISM:制造业PMI(报告期:2025年10月)",
      "content": null,
      "category": "经济数据",
      "importance": 4,
      "country": "美国",
      "city": null,
      "stocks": [],
      "concepts": [],
      "themes": [],
      "data_status": "ACTIVE",
      "is_new": true,
      "discovery_date": "2025-10-11",
      "raw_data": {
        "Name": "美国：ISM:制造业PMI(报告期:2025年10月)",
        "City": "美国"
      },
      "created_at": "2025-10-11T14:11:59.732630"
    },
    {
      "platform": "eastmoney",
      "event_id": "em_jjsj_20251103230000_2541489726609435819",
      "original_id": "2025-11-03 23:00:00_美国：ISM：制造业PMI：物价(报告期:2025年10月)",
      "event_date": "2025-11-03",
      "event_time": "23:00:00",
      "event_datetime": "2025-11-03 23:00:00",
      "title": "美国：ISM：制造业PMI：物价(报告期:2025年10月)",
      "content": null,
      "category": "经济数据",
      "importance": 4,
      "country": "美国",
      "city": null,
      "stocks": [],
      "concepts": [],
      "themes": [],
      "data_status": "ACTIVE",
      "is_new": true,
      "discovery_date": "2025-10-11",
      "raw_data": {
        "Name": "美国：ISM：制造业PMI：物价(报告期:2025年10月)",
        "City": "美国"
      },
      "created_at": "2025-10-11T14:11:59.732638"
    },
    {
      "platform": "eastmoney",
      "event_id": "em_jjsj_20251103230000_8500440489384268511",
      "original_id": "2025-11-03 23:00:00_美国：ISM：制造业PMI：新订单(报告期:2025年10月)",
      "event_date": "2025-11-03",
      "event_time": "23:00:00",
      "event_datetime": "2025-11-03 23:00:00",
      "title": "美国：ISM：制造业PMI：新订单(报告期:2025年10月)",
      "content": null,
      "category": "经济数据",
      "importance": 4,
      "country": "美国",
      "city": null,
      "stocks": [],
      "concepts": [],
      "themes": [],
      "data_status": "ACTIVE",
      "is_new": true,
      "discovery_date": "2025-10-11",
      "raw_data": {
        "Name": "美国：ISM：制造业PMI：新订单(报告期:2025年10月)",
        "City": "美国"
      },
      "created_at": "2025-10-11T14:11:59.732645"
    },
    {
      "platform": "eastmoney",
      "event_id": "em_jjsj_20251103230000_-1526329695852390276",
      "original_id": "2025-11-03 23:00:00_美国：ISM：制造业PMI：产出(报告期:2025年10月)",
      "event_date": "2025-11-03",
      "event_time": "23:00:00",
      "event_datetime": "2025-11-03 23:00:00",
      "title": "美国：ISM：制造业PMI：产出(报告期:2025年10月)",
      "content": null,
      "category": "经济数据",
      "importance": 4,
      "country": "美国",
      "city": null,
      "stocks": [],
      "concepts": [],
      "themes": [],
      "data_status": "ACTIVE",
      "is_new": true,
      "discovery_date": "2025-10-11",
      "raw_data": {
        "Name": "美国：ISM：制造业PMI：产出(报告期:2025年10月)",
        "City": "美国"
      },
      "created_at": "2025-10-11T14:11:59.732652"
    },
    {
      "platform": "eastmoney",
      "event_id": "em_jjsj_20251103230000_-7046600687246990086",
      "original_id": "2025-11-03 23:00:00_美国：ISM：制造业PMI：就业(报告期:2025年10月)",
      "event_date": "2025-11-03",
      "event_time": "23:00:00",
      "event_datetime": "2025-11-03 23:00:00",
      "title": "美国：ISM：制造业PMI：就业(报告期:2025年10月)",
      "content": null,
      "category": "经济数据",
      "importance": 4,
      "country": "美国",
      "city": null,
      "stocks": [],
      "concepts": [],
      "themes": [],
      "data_status": "ACTIVE",
      "is_new": true,
      "discovery_date": "2025-10-11",
      "raw_data": {
        "Name": "美国：ISM：制造业PMI：就业(报告期:2025年10月)",
        "City": "美国"
      },
      "created_at": "2025-10-11T14:11:59.732659"
    }
  ]
}